Metadata-Version: 2.1
Name: xcpythontool
Version: 0.0.7
Summary: 测试上传pip
Home-page: https://github.com/19933139420/xcpythontest.git
Author: xuxuechao
Author-email: 932829703@qq.com
License: MIT Licence
Keywords: xxc,play
Platform: any
